{"is_source_file": true, "format": "JavaScript (React JSX)", "description": "This is the main application component (App.jsx) for a React project. It sets up the theme, layout with Navbar and Sidebar, and manages light/dark mode toggling.", "external_files": ["./components/layout/Navbar", "./components/layout/Sidebar"], "external_methods": ["useMemo", "useState", "Outlet", "createTheme"], "published": ["default"], "classes": [], "methods": [{"name": "App()", "description": "Main React functional component that defines the app layout, theme, and mode toggling.", "scope": "", "scopeKind": ""}, {"name": "toggleMode", "description": "Function that toggles between light and dark themes."}], "calls": ["useMemo", "useState", "createTheme", "setMode", "Outlet", "Navbar", "Sidebar"], "search-terms": ["App.jsx", "theme", "Navbar", "Sidebar", "light/dark mode", "Mui", "Material UI", "React layout"], "state": 2, "file_id": 15, "knowledge_revision": 32, "git_revision": "", "ctags": [{"_type": "tag", "name": "App", "path": "/home/kavia/workspace/code-generation/career-navigator-platform-209461-209474/frontend_react/src/App.jsx", "pattern": "/^export default function App() {$/", "language": "JavaScript", "kind": "function", "signature": "()"}, {"_type": "tag", "name": "main", "path": "/home/kavia/workspace/code-generation/career-navigator-platform-209461-209474/frontend_react/src/App.jsx", "pattern": "/^  primary: { main: '#3b82f6' },$/", "language": "JavaScript", "kind": "property", "scope": "palette.primary", "scopeKind": "class"}, {"_type": "tag", "name": "main", "path": "/home/kavia/workspace/code-generation/career-navigator-platform-209461-209474/frontend_react/src/App.jsx", "pattern": "/^  secondary: { main: '#64748b' },$/", "language": "JavaScript", "kind": "property", "scope": "palette.secondary", "scopeKind": "class"}, {"_type": "tag", "name": "main", "path": "/home/kavia/workspace/code-generation/career-navigator-platform-209461-209474/frontend_react/src/App.jsx", "pattern": "/^  success: { main: '#06b6d4' }$/", "language": "JavaScript", "kind": "property", "scope": "palette.success", "scopeKind": "class"}, {"_type": "tag", "name": "palette", "path": "/home/kavia/workspace/code-generation/career-navigator-platform-209461-209474/frontend_react/src/App.jsx", "pattern": "/^const palette = {$/", "language": "JavaScript", "kind": "class"}, {"_type": "tag", "name": "primary", "path": "/home/kavia/workspace/code-generation/career-navigator-platform-209461-209474/frontend_react/src/App.jsx", "pattern": "/^  primary: { main: '#3b82f6' },$/", "language": "JavaScript", "kind": "class", "scope": "palette", "scopeKind": "class"}, {"_type": "tag", "name": "secondary", "path": "/home/kavia/workspace/code-generation/career-navigator-platform-209461-209474/frontend_react/src/App.jsx", "pattern": "/^  secondary: { main: '#64748b' },$/", "language": "JavaScript", "kind": "class", "scope": "palette", "scopeKind": "class"}, {"_type": "tag", "name": "success", "path": "/home/kavia/workspace/code-generation/career-navigator-platform-209461-209474/frontend_react/src/App.jsx", "pattern": "/^  success: { main: '#06b6d4' }$/", "language": "JavaScript", "kind": "class", "scope": "palette", "scopeKind": "class"}, {"_type": "tag", "name": "theme", "path": "/home/kavia/workspace/code-generation/career-navigator-platform-209461-209474/frontend_react/src/App.jsx", "pattern": "/^    <ThemeProvider theme={theme}>$/", "language": "JavaScript", "kind": "field", "scope": "App.AnonymousClass98d196f50101", "scopeKind": "class"}], "hash": "5df914f31ef2a9ba17244697b6175e90", "format-version": 4, "code-base-name": "frontend_react", "filename": "frontend_react/src/App.jsx", "fields": [{"name": "primary: { main: '#3b82f6' },", "scope": "palette.primary", "scopeKind": "class", "description": "unavailable"}, {"name": "secondary: { main: '#64748b' },", "scope": "palette.secondary", "scopeKind": "class", "description": "unavailable"}, {"name": "success: { main: '#06b6d4' }", "scope": "palette.success", "scopeKind": "class", "description": "unavailable"}, {"name": "<ThemeProvider theme={theme}>", "scope": "App.AnonymousClass98d196f50101", "scopeKind": "class", "description": "unavailable"}], "revision_history": [{"32": ""}]}